filtering_pipeline/__init__.py
filtering_pipeline/factory.py
filtering_pipeline/filters/__init__.py
filtering_pipeline/filters/abstract_filter.py
filtering_pipeline/filters/catalog_filter/subpipeline_filter.py
filtering_pipeline/filters/catalog_source/source_list.py
filtering_pipeline/pipe/__init__.py
filtering_pipeline/pipe/abstractpipeline.py
filtering_pipeline/pipe/pipeline.py
filtering_pipeline/pipe/subpipeline.py
filtering_pipeline/utils/to_dict.py
filtering_pipeline-0.2.2.dist-info/WHEEL
filtering_pipeline-0.2.2.dist-info/METADATA
filtering_pipeline-0.2.2.dist-info/RECORD
